{"config":{"output_file":null,"full_docs":false,"pub_only":true,"reachable_only":true,"distro_crate":false,"signatures":false,"borrow_data":false},"version":"0.19.0","compilation":{"directory":"/home/hustccc/.cargo/registry/src/mirrors.tuna.tsinghua.edu.cn-df7c3c540f42cdbd/vcell-0.1.2","program":"/home/hustccc/.rustup/toolchains/nightly-2020-06-04-x86_64-unknown-linux-gnu/bin/rls","arguments":["--crate-name","vcell","/home/hustccc/.cargo/registry/src/mirrors.tuna.tsinghua.edu.cn-df7c3c540f42cdbd/vcell-0.1.2/src/lib.rs","--json=diagnostic-rendered-ansi","--crate-type","lib","--emit=dep-info,metadata","-Cembed-bitcode=no","-C","debuginfo=2","-C","metadata=4c1f98163a677390","-C","extra-filename=-4c1f98163a677390","--out-dir","/home/hustccc/xv6-k210/bootloader/SBI/rustsbi-k210/target/rls/riscv64gc-unknown-none-elf/debug/deps","--target","riscv64gc-unknown-none-elf","-L","dependency=/home/hustccc/xv6-k210/bootloader/SBI/rustsbi-k210/target/rls/riscv64gc-unknown-none-elf/debug/deps","-L","dependency=/home/hustccc/xv6-k210/bootloader/SBI/rustsbi-k210/target/rls/debug/deps","--cap-lints","allow","--error-format=json","--sysroot","/home/hustccc/.rustup/toolchains/nightly-2020-06-04-x86_64-unknown-linux-gnu"],"output":"/home/hustccc/xv6-k210/bootloader/SBI/rustsbi-k210/target/rls/riscv64gc-unknown-none-elf/debug/deps/libvcell-4c1f98163a677390.rmeta"},"prelude":{"crate_id":{"name":"vcell","disambiguator":[17822269093167617112,11334295192971302155]},"crate_root":"/home/hustccc/.cargo/registry/src/mirrors.tuna.tsinghua.edu.cn-df7c3c540f42cdbd/vcell-0.1.2/src","external_crates":[{"file_name":"/home/hustccc/.cargo/registry/src/mirrors.tuna.tsinghua.edu.cn-df7c3c540f42cdbd/vcell-0.1.2/src/lib.rs","num":1,"id":{"name":"core","disambiguator":[226134479413951811,2067214400362673723]}},{"file_name":"/home/hustccc/.cargo/registry/src/mirrors.tuna.tsinghua.edu.cn-df7c3c540f42cdbd/vcell-0.1.2/src/lib.rs","num":2,"id":{"name":"compiler_builtins","disambiguator":[7013652143555253117,14040640170877995705]}},{"file_name":"/home/hustccc/.cargo/registry/src/mirrors.tuna.tsinghua.edu.cn-df7c3c540f42cdbd/vcell-0.1.2/src/lib.rs","num":3,"id":{"name":"rustc_std_workspace_core","disambiguator":[11836271775442074852,5296054539026637499]}}],"span":{"file_name":"/home/hustccc/.cargo/registry/src/mirrors.tuna.tsinghua.edu.cn-df7c3c540f42cdbd/vcell-0.1.2/src/lib.rs","byte_start":0,"byte_end":1296,"line_start":1,"line_end":48,"column_start":1,"column_end":2}},"imports":[],"defs":[{"kind":"Mod","id":{"krate":0,"index":0},"span":{"file_name":"/home/hustccc/.cargo/registry/src/mirrors.tuna.tsinghua.edu.cn-df7c3c540f42cdbd/vcell-0.1.2/src/lib.rs","byte_start":0,"byte_end":1296,"line_start":1,"line_end":48,"column_start":1,"column_end":2},"name":"","qualname":"::","value":"/home/hustccc/.cargo/registry/src/mirrors.tuna.tsinghua.edu.cn-df7c3c540f42cdbd/vcell-0.1.2/src/lib.rs","parent":null,"children":[{"krate":0,"index":1},{"krate":0,"index":2},{"krate":0,"index":3},{"krate":0,"index":4},{"krate":0,"index":5},{"krate":0,"index":6},{"krate":0,"index":9}],"decl_id":null,"docs":" Just like [`Cell`] but with [volatile] read / write operations","sig":null,"attributes":[{"value":"! Just like [`Cell`] but with [volatile] read / write operations","span":{"file_name":"/home/hustccc/.cargo/registry/src/mirrors.tuna.tsinghua.edu.cn-df7c3c540f42cdbd/vcell-0.1.2/src/lib.rs","byte_start":0,"byte_end":66,"line_start":1,"line_end":1,"column_start":1,"column_end":67}},{"value":"!","span":{"file_name":"/home/hustccc/.cargo/registry/src/mirrors.tuna.tsinghua.edu.cn-df7c3c540f42cdbd/vcell-0.1.2/src/lib.rs","byte_start":67,"byte_end":70,"line_start":2,"line_end":2,"column_start":1,"column_end":4}},{"value":"! [`Cell`]: https://doc.rust-lang.org/std/cell/struct.Cell.html","span":{"file_name":"/home/hustccc/.cargo/registry/src/mirrors.tuna.tsinghua.edu.cn-df7c3c540f42cdbd/vcell-0.1.2/src/lib.rs","byte_start":71,"byte_end":136,"line_start":3,"line_end":3,"column_start":1,"column_end":66}},{"value":"! [volatile]: https://doc.rust-lang.org/std/ptr/fn.read_volatile.html","span":{"file_name":"/home/hustccc/.cargo/registry/src/mirrors.tuna.tsinghua.edu.cn-df7c3c540f42cdbd/vcell-0.1.2/src/lib.rs","byte_start":137,"byte_end":208,"line_start":4,"line_end":4,"column_start":1,"column_end":72}},{"value":"deny(missing_docs)","span":{"file_name":"/home/hustccc/.cargo/registry/src/mirrors.tuna.tsinghua.edu.cn-df7c3c540f42cdbd/vcell-0.1.2/src/lib.rs","byte_start":210,"byte_end":232,"line_start":6,"line_end":6,"column_start":1,"column_end":23}},{"value":"deny(warnings)","span":{"file_name":"/home/hustccc/.cargo/registry/src/mirrors.tuna.tsinghua.edu.cn-df7c3c540f42cdbd/vcell-0.1.2/src/lib.rs","byte_start":233,"byte_end":251,"line_start":7,"line_end":7,"column_start":1,"column_end":19}},{"value":"no_std","span":{"file_name":"/home/hustccc/.cargo/registry/src/mirrors.tuna.tsinghua.edu.cn-df7c3c540f42cdbd/vcell-0.1.2/src/lib.rs","byte_start":252,"byte_end":262,"line_start":8,"line_end":8,"column_start":1,"column_end":11}}]},{"kind":"Struct","id":{"krate":0,"index":6},"span":{"file_name":"/home/hustccc/.cargo/registry/src/mirrors.tuna.tsinghua.edu.cn-df7c3c540f42cdbd/vcell-0.1.2/src/lib.rs","byte_start":528,"byte_end":540,"line_start":17,"line_end":17,"column_start":12,"column_end":24},"name":"VolatileCell","qualname":"::VolatileCell","value":"VolatileCell {  }","parent":null,"children":[{"krate":0,"index":8}],"decl_id":null,"docs":" Just like [`Cell`] but with [volatile] read / write operations","sig":null,"attributes":[{"value":"/ Just like [`Cell`] but with [volatile] read / write operations","span":{"file_name":"/home/hustccc/.cargo/registry/src/mirrors.tuna.tsinghua.edu.cn-df7c3c540f42cdbd/vcell-0.1.2/src/lib.rs","byte_start":308,"byte_end":374,"line_start":13,"line_end":13,"column_start":1,"column_end":67}},{"value":"/","span":{"file_name":"/home/hustccc/.cargo/registry/src/mirrors.tuna.tsinghua.edu.cn-df7c3c540f42cdbd/vcell-0.1.2/src/lib.rs","byte_start":375,"byte_end":378,"line_start":14,"line_end":14,"column_start":1,"column_end":4}},{"value":"/ [`Cell`]: https://doc.rust-lang.org/std/cell/struct.Cell.html","span":{"file_name":"/home/hustccc/.cargo/registry/src/mirrors.tuna.tsinghua.edu.cn-df7c3c540f42cdbd/vcell-0.1.2/src/lib.rs","byte_start":379,"byte_end":444,"line_start":15,"line_end":15,"column_start":1,"column_end":66}},{"value":"/ [volatile]: https://doc.rust-lang.org/std/ptr/fn.read_volatile.html","span":{"file_name":"/home/hustccc/.cargo/registry/src/mirrors.tuna.tsinghua.edu.cn-df7c3c540f42cdbd/vcell-0.1.2/src/lib.rs","byte_start":445,"byte_end":516,"line_start":16,"line_end":16,"column_start":1,"column_end":72}}]},{"kind":"Method","id":{"krate":0,"index":11},"span":{"file_name":"/home/hustccc/.cargo/registry/src/mirrors.tuna.tsinghua.edu.cn-df7c3c540f42cdbd/vcell-0.1.2/src/lib.rs","byte_start":682,"byte_end":685,"line_start":23,"line_end":23,"column_start":18,"column_end":21},"name":"new","qualname":"<VolatileCell<T>>::new","value":"fn (value: T) -> Self","parent":null,"children":[],"decl_id":null,"docs":" Creates a new `VolatileCell` containing the given value\n","sig":null,"attributes":[{"value":"/ Creates a new `VolatileCell` containing the given value","span":{"file_name":"/home/hustccc/.cargo/registry/src/mirrors.tuna.tsinghua.edu.cn-df7c3c540f42cdbd/vcell-0.1.2/src/lib.rs","byte_start":605,"byte_end":664,"line_start":22,"line_end":22,"column_start":5,"column_end":64}}]},{"kind":"Method","id":{"krate":0,"index":12},"span":{"file_name":"/home/hustccc/.cargo/registry/src/mirrors.tuna.tsinghua.edu.cn-df7c3c540f42cdbd/vcell-0.1.2/src/lib.rs","byte_start":847,"byte_end":850,"line_start":29,"line_end":29,"column_start":12,"column_end":15},"name":"get","qualname":"<VolatileCell<T>>::get","value":"fn (&self) -> T","parent":null,"children":[],"decl_id":null,"docs":" Returns a copy of the contained value\n","sig":null,"attributes":[{"value":"/ Returns a copy of the contained value","span":{"file_name":"/home/hustccc/.cargo/registry/src/mirrors.tuna.tsinghua.edu.cn-df7c3c540f42cdbd/vcell-0.1.2/src/lib.rs","byte_start":772,"byte_end":813,"line_start":27,"line_end":27,"column_start":5,"column_end":46}},{"value":"inline(always)","span":{"file_name":"/home/hustccc/.cargo/registry/src/mirrors.tuna.tsinghua.edu.cn-df7c3c540f42cdbd/vcell-0.1.2/src/lib.rs","byte_start":818,"byte_end":835,"line_start":28,"line_end":28,"column_start":5,"column_end":22}}]},{"kind":"Method","id":{"krate":0,"index":13},"span":{"file_name":"/home/hustccc/.cargo/registry/src/mirrors.tuna.tsinghua.edu.cn-df7c3c540f42cdbd/vcell-0.1.2/src/lib.rs","byte_start":1020,"byte_end":1023,"line_start":37,"line_end":37,"column_start":12,"column_end":15},"name":"set","qualname":"<VolatileCell<T>>::set","value":"fn (&self, value: T) -> ()","parent":null,"children":[],"decl_id":null,"docs":" Sets the contained value\n","sig":null,"attributes":[{"value":"/ Sets the contained value","span":{"file_name":"/home/hustccc/.cargo/registry/src/mirrors.tuna.tsinghua.edu.cn-df7c3c540f42cdbd/vcell-0.1.2/src/lib.rs","byte_start":958,"byte_end":986,"line_start":35,"line_end":35,"column_start":5,"column_end":33}},{"value":"inline(always)","span":{"file_name":"/home/hustccc/.cargo/registry/src/mirrors.tuna.tsinghua.edu.cn-df7c3c540f42cdbd/vcell-0.1.2/src/lib.rs","byte_start":991,"byte_end":1008,"line_start":36,"line_end":36,"column_start":5,"column_end":22}}]},{"kind":"Method","id":{"krate":0,"index":14},"span":{"file_name":"/home/hustccc/.cargo/registry/src/mirrors.tuna.tsinghua.edu.cn-df7c3c540f42cdbd/vcell-0.1.2/src/lib.rs","byte_start":1238,"byte_end":1244,"line_start":45,"line_end":45,"column_start":12,"column_end":18},"name":"as_ptr","qualname":"<VolatileCell<T>>::as_ptr","value":"fn (&self) -> *mut T","parent":null,"children":[],"decl_id":null,"docs":" Returns a raw pointer to the underlying data in the cell\n","sig":null,"attributes":[{"value":"/ Returns a raw pointer to the underlying data in the cell","span":{"file_name":"/home/hustccc/.cargo/registry/src/mirrors.tuna.tsinghua.edu.cn-df7c3c540f42cdbd/vcell-0.1.2/src/lib.rs","byte_start":1144,"byte_end":1204,"line_start":43,"line_end":43,"column_start":5,"column_end":65}},{"value":"inline(always)","span":{"file_name":"/home/hustccc/.cargo/registry/src/mirrors.tuna.tsinghua.edu.cn-df7c3c540f42cdbd/vcell-0.1.2/src/lib.rs","byte_start":1209,"byte_end":1226,"line_start":44,"line_end":44,"column_start":5,"column_end":22}}]}],"impls":[{"id":0,"kind":"Inherent","span":{"file_name":"/home/hustccc/.cargo/registry/src/mirrors.tuna.tsinghua.edu.cn-df7c3c540f42cdbd/vcell-0.1.2/src/lib.rs","byte_start":583,"byte_end":595,"line_start":21,"line_end":21,"column_start":9,"column_end":21},"value":"","parent":null,"children":[{"krate":0,"index":11},{"krate":0,"index":12},{"krate":0,"index":13},{"krate":0,"index":14}],"docs":"","sig":null,"attributes":[]}],"refs":[],"macro_refs":[],"relations":[{"span":{"file_name":"/home/hustccc/.cargo/registry/src/mirrors.tuna.tsinghua.edu.cn-df7c3c540f42cdbd/vcell-0.1.2/src/lib.rs","byte_start":583,"byte_end":595,"line_start":21,"line_end":21,"column_start":9,"column_end":21},"kind":{"Impl":{"id":0}},"from":{"krate":0,"index":6},"to":{"krate":4294967295,"index":4294967295}}]}